blackhc/laaos/__init__.py
blackhc.laaos-1.1.0.dist-info/LICENSE
blackhc.laaos-1.1.0.dist-info/METADATA
blackhc.laaos-1.1.0.dist-info/WHEEL
blackhc.laaos-1.1.0.dist-info/top_level.txt
blackhc.laaos-1.1.0.dist-info/RECORD
