Metadata-Version: 2.1
Name: blackhc.laaos
Version: 1.1.0
Summary: "Log as append-only source" logger
Home-page: https://github.com/blackhc/laaos
Author: Andreas @blackhc Kirsch
Author-email: blackhc+laaos@gmail.com
License: MIT
Keywords: logging
Platform: UNKNOWN
Classifier: Development Status :: 5 - Production/Stable
Classifier: Intended Audience :: Developers
Classifier: Intended Audience :: Science/Research
Classifier: Topic :: Software Development :: Libraries :: Python Modules
Classifier: License :: OSI Approved :: MIT License
Classifier: Programming Language :: Python :: 3.6
Provides-Extra: dev
Requires-Dist: check-manifest ; extra == 'dev'
Provides-Extra: test
Requires-Dist: coverage ; extra == 'test'
Requires-Dist: pytest ; extra == 'test'
